{
  "scene_id": "37-373-3734",
  "scene_name": "装配安装-船用发动机配件-重载精密部件",
  "total_steps": 42,
  "action_sequence": [
    {
      "step_order": 1,
      "human_description": "工人从待命区行走至部件装配工位",
      "l1_id": "L1-01",
      "l1_name": "全身位移",
      "l2_id": "L2-01-01",
      "l2_name": "平地直行",
      "l3_id": "L3-01-01-001",
      "l3_name": "行走-车间环氧地坪-匀速",
      "is_new_l3": true,
      "boundary_note": null,
      "parallel_with": null,
      "duration_estimate": "5-15"
    },
    {
      "step_order": 2,
      "human_description": "在工位标定点精确停位",
      "l1_id": "L1-01",
      "l1_name": "全身位移",
      "l2_id": "L2-01-08",
      "l2_name": "精确停位",
      "l3_id": "L3-01-08-001",
      "l3_name": "停位-装配工位标定点-厘米级",
      "is_new_l3": true,
      "boundary_note": null,
      "parallel_with": null,
      "duration_estimate": "1-2"
    },
    {
      "step_order": 3,
      "human_description": "注视查看作业指导书上的装配顺序和扭矩要求",
      "l1_id": "L1-09",
      "l1_name": "感知定位运动",
      "l2_id": "L2-09-07",
      "l2_name": "标识读取定位",
      "l3_id": "L3-09-07-001",
      "l3_name": "读取-装配作业指导书-工艺参数",
      "is_new_l3": true,
      "boundary_note": null,
      "parallel_with": null,
      "duration_estimate": "5-10"
    },
    {
      "step_order": 4,
      "human_description": "转体面向缸套存放区",
      "l1_id": "L1-02",
      "l1_name": "躯体姿态调整",
      "l2_id": "L2-02-04",
      "l2_name": "躯干旋转",
      "l3_id": "L3-02-04-001",
      "l3_name": "转体-90度-向物料区",
      "is_new_l3": true,
      "boundary_note": null,
      "parallel_with": null,
      "duration_estimate": "1-2"
    },
    {
      "step_order": 5,
      "human_description": "行走至起重设备操控位置",
      "l1_id": "L1-01",
      "l1_name": "全身位移",
      "l2_id": "L2-01-01",
      "l2_name": "平地直行",
      "l3_id": "L3-01-01-001",
      "l3_name": "行走-车间环氧地坪-匀速",
      "is_new_l3": false,
      "boundary_note": null,
      "parallel_with": null,
      "duration_estimate": "3-8"
    },
    {
      "step_order": 6,
      "human_description": "伸手握住行车/天车遥控器",
      "l1_id": "L1-03",
      "l1_name": "上肢空间运动",
      "l2_id": "L2-03-01",
      "l2_name": "空载伸达",
      "l3_id": "L3-03-01-001",
      "l3_name": "伸达-起重遥控器悬挂位-无障碍",
      "is_new_l3": true,
      "boundary_note": null,
      "parallel_with": null,
      "duration_estimate": "1-2"
    },
    {
      "step_order": 7,
      "human_description": "功能握持行车遥控器",
      "l1_id": "L1-04",
      "l1_name": "手部抓握操控",
      "l2_id": "L2-04-03",
      "l2_name": "工具功能握持",
      "l3_id": "L3-04-03-001",
      "l3_name": "工具握持-起重遥控器-操控功能姿",
      "is_new_l3": true,
      "boundary_note": null,
      "parallel_with": null,
      "duration_estimate": "1-2"
    },
    {
      "step_order": 8,
      "human_description": "点压遥控器按钮移动吊钩至缸套上方",
      "l1_id": "L1-05",
      "l1_name": "线性力施加",
      "l2_id": "L2-05-01",
      "l2_name": "点压触发",
      "l3_id": "L3-05-01-001",
      "l3_name": "点压-起重遥控按钮-轻力度",
      "is_new_l3": true,
      "boundary_note": null,
      "parallel_with": null,
      "duration_estimate": "10-30"
    },
    {
      "step_order": 9,
      "human_description": "注视确认吊钩已到达缸套正上方",
      "l1_id": "L1-09",
      "l1_name": "感知定位运动",
      "l2_id": "L2-09-01",
      "l2_name": "视觉注视对准",
      "l3_id": "L3-09-01-001",
      "l3_name": "注视-起重设备吊钩-位置确认",
      "is_new_l3": true,
      "boundary_note": null,
      "parallel_with": null,
      "duration_estimate": "2-3"
    },
    {
      "step_order": 10,
      "human_description": "释放遥控器暂放",
      "l1_id": "L1-04",
      "l1_name": "手部抓握操控",
      "l2_id": "L2-04-07",
      "l2_name": "受控释放",
      "l3_id": "L3-04-07-001",
      "l3_name": "释放-渐进松指-遥控器悬挂",
      "is_new_l3": true,
      "boundary_note": null,
      "parallel_with": null,
      "duration_estimate": "1-2"
    },
    {
      "step_order": 11,
      "human_description": "弯腰俯身至缸套吊耳高度",
      "l1_id": "L1-02",
      "l1_name": "躯体姿态调整",
      "l2_id": "L2-02-02",
      "l2_name": "弯腰俯身",
      "l3_id": "L3-02-02-001",
      "l3_name": "俯身-中度前屈-工件吊耳高度",
      "is_new_l3": true,
      "boundary_note": null,
      "parallel_with": null,
      "duration_estimate": "1-2"
    },
    {
      "step_order": 12,
      "human_description": "伸手拿取吊具钩环",
      "l1_id": "L1-03",
      "l1_name": "上肢空间运动",
      "l2_id": "L2-03-01",
      "l2_name": "空载伸达",
      "l3_id": "L3-03-01-002",
      "l3_name": "伸达-吊具钩环-短距直线",
      "is_new_l3": true,
      "boundary_note": null,
      "parallel_with": null,
      "duration_estimate": "1-2"
    },
    {
      "step_order": 13,
      "human_description": "力量抓握吊具钩环",
      "l1_id": "L1-04",
      "l1_name": "手部抓握操控",
      "l2_id": "L2-04-01",
      "l2_name": "力量抓握",
      "l3_id": "L3-04-01-001",
      "l3_name": "力握-圆环-直径15至30mm",
      "is_new_l3": true,
      "boundary_note": null,
      "parallel_with": null,
      "duration_estimate": "1-2"
    },
    {
      "step_order": 14,
      "human_description": "将吊具钩环挂入缸套吊耳孔",
      "l1_id": "L1-07",
      "l1_name": "约束路径操作",
      "l2_id": "L2-07-01",
      "l2_name": "直线插入",
      "l3_id": "L3-07-01-001",
      "l3_name": "插入-吊钩入吊耳孔-间隙5mm",
      "is_new_l3": true,
      "boundary_note": null,
      "parallel_with": null,
      "duration_estimate": "2-4"
    },
    {
      "step_order": 15,
      "human_description": "起身恢复站立姿态",
      "l1_id": "L1-02",
      "l1_name": "躯体姿态调整",
      "l2_id": "L2-02-02",
      "l2_name": "弯腰俯身",
      "l3_id": "L3-02-02-002",
      "l3_name": "俯身-起身复位-站立姿态",
      "is_new_l3": true,
      "boundary_note": "俯身的逆过程仍归入L2-02-02",
      "parallel_with": null,
      "duration_estimate": "1-2"
    },
    {
      "step_order": 16,
      "human_description": "再次握住行车遥控器",
      "l1_id": "L1-04",
      "l1_name": "手部抓握操控",
      "l2_id": "L2-04-03",
      "l2_name": "工具功能握持",
      "l3_id": "L3-04-03-001",
      "l3_name": "工具握持-起重遥控器-操控功能姿",
      "is_new_l3": false,
      "boundary_note": null,
      "parallel_with": null,
      "duration_estimate": "1-2"
    },
    {
      "step_order": 17,
      "human_description": "点压遥控器起吊缸套离开地面",
      "l1_id": "L1-05",
      "l1_name": "线性力施加",
      "l2_id": "L2-05-01",
      "l2_name": "点压触发",
      "l3_id": "L3-05-01-001",
      "l3_name": "点压-起重遥控按钮-轻力度",
      "is_new_l3": false,
      "boundary_note": null,
      "parallel_with": null,
      "duration_estimate": "5-10"
    },
    {
      "step_order": 18,
      "human_description": "边行走边操控遥控器引导缸套移向发动机缸体",
      "l1_id": "L1-01",
      "l1_name": "全身位移",
      "l2_id": "L2-01-07",
      "l2_name": "负载行走",
      "l3_id": "L3-01-07-001",
      "l3_name": "负载行走-起重引导-遥控持握",
      "is_new_l3": true,
      "boundary_note": "[边界判定]虽然缸套由起重机承载，但工人需边走边操控遥控器引导，属于特殊形式的负载协调行走",
      "parallel_with": null,
      "duration_estimate": "15-30"
    },
    {
      "step_order": 19,
      "human_description": "在缸体装配位精确停位",
      "l1_id": "L1-01",
      "l1_name": "全身位移",
      "l2_id": "L2-01-08",
      "l2_name": "精确停位",
      "l3_id": "L3-01-08-001",
      "l3_name": "停位-装配工位标定点-厘米级",
      "is_new_l3": false,
      "boundary_note": null,
      "parallel_with": null,
      "duration_estimate": "1-2"
    },
    {
      "step_order": 20,
      "human_description": "单手抵持悬吊的缸套防止晃动",
      "l1_id": "L1-05",
      "l1_name": "线性力施加",
      "l2_id": "L2-05-06",
      "l2_name": "静态抵持",
      "l3_id": "L3-05-06-001",
      "l3_name": "抵持-悬吊重件-水平稳定",
      "is_new_l3": true,
      "boundary_note": null,
      "parallel_with": null,
      "duration_estimate": "5-15"
    },
    {
      "step_order": 21,
      "human_description": "注视对准缸套与缸体安装孔的相对位置",
      "l1_id": "L1-09",
      "l1_name": "感知定位运动",
      "l2_id": "L2-09-01",
      "l2_name": "视觉注视对准",
      "l3_id": "L3-09-01-002",
      "l3_name": "注视-装配配合面-对准确认",
      "is_new_l3": true,
      "boundary_note": null,
      "parallel_with": "20",
      "duration_estimate": "3-5"
    },
    {
      "step_order": 22,
      "human_description": "微调遥控器使缸套精确对准缸体孔",
      "l1_id": "L1-05",
      "l1_name": "线性力施加",
      "l2_id": "L2-05-01",
      "l2_name": "点压触发",
      "l3_id": "L3-05-01-002",
      "l3_name": "点压-起重遥控微动按钮-精确定位",
      "is_new_l3": true,
      "boundary_note": null,
      "parallel_with": null,
      "duration_estimate": "10-30"
    },
    {
      "step_order": 23,
      "human_description": "双手引导缸套进入缸体安装孔",
      "l1_id": "L1-07",
      "l1_name": "约束路径操作",
      "l2_id": "L2-07-01",
      "l2_name": "直线插入",
      "l3_id": "L3-07-01-002",
      "l3_name": "插入-缸套入缸体孔-精密间隙配合",
      "is_new_l3": true,
      "boundary_note": null,
      "parallel_with": null,
      "duration_estimate": "20-60"
    },
    {
      "step_order": 24,
      "human_description": "贴近检视缸套与缸体配合面的贴合状态",
      "l1_id": "L1-09",
      "l1_name": "感知定位运动",
      "l2_id": "L2-09-02",
      "l2_name": "近距贴近检视",
      "l3_id": "L3-09-02-001",
      "l3_name": "贴检-配合面间隙-装配到位确认",
      "is_new_l3": true,
      "boundary_note": null,
      "parallel_with": null,
      "duration_estimate": "3-5"
    },
    {
      "step_order": 25,
      "human_description": "松开吊具钩环脱离缸套吊耳",
      "l1_id": "L1-07",
      "l1_name": "约束路径操作",
      "l2_id": "L2-07-02",
      "l2_name": "直线抽出",
      "l3_id": "L3-07-02-001",
      "l3_name": "抽出-吊钩脱吊耳-无阻力",
      "is_new_l3": true,
      "boundary_note": null,
      "parallel_with": null,
      "duration_estimate": "2-4"
    },
    {
      "step_order": 26,
      "human_description": "行走至工具架取活塞连杆组件专用吊具",
      "l1_id": "L1-01",
      "l1_name": "全身位移",
      "l2_id": "L2-01-01",
      "l2_name": "平地直行",
      "l3_id": "L3-01-01-001",
      "l3_name": "行走-车间环氧地坪-匀速",
      "is_new_l3": false,
      "boundary_note": null,
      "parallel_with": null,
      "duration_estimate": "3-8"
    },
    {
      "step_order": 27,
      "human_description": "伸手拿取扭矩扳手",
      "l1_id": "L1-03",
      "l1_name": "上肢空间运动",
      "l2_id": "L2-03-01",
      "l2_name": "空载伸达",
      "l3_id": "L3-03-01-003",
      "l3_name": "伸达-工具架工具位-短距直线",
      "is_new_l3": true,
      "boundary_note": null,
      "parallel_with": null,
      "duration_estimate": "1-2"
    },
    {
      "step_order": 28,
      "human_description": "功能握持扭矩扳手手柄",
      "l1_id": "L1-04",
      "l1_name": "手部抓握操控",
      "l2_id": "L2-04-03",
      "l2_name": "工具功能握持",
      "l3_id": "L3-04-03-002",
      "l3_name": "工具握持-扭矩扳手-旋拧功能姿",
      "is_new_l3": true,
      "boundary_note": null,
      "parallel_with": null,
      "duration_estimate": "1-2"
    },
    {
      "step_order": 29,
      "human_description": "负载转移扭矩扳手至装配工位",
      "l1_id": "L1-03",
      "l1_name": "上肢空间运动",
      "l2_id": "L2-03-02",
      "l2_name": "单臂负载转移",
      "l3_id": "L3-03-02-001",
      "l3_name": "转移-手持工具-近距",
      "is_new_l3": true,
      "boundary_note": null,
      "parallel_with": null,
      "duration_estimate": "3-5"
    },
    {
      "step_order": 30,
      "human_description": "弯腰俯身至连杆螺栓高度",
      "l1_id": "L1-02",
      "l1_name": "躯体姿态调整",
      "l2_id": "L2-02-02",
      "l2_name": "弯腰俯身",
      "l3_id": "L3-02-02-003",
      "l3_name": "俯身-深度前屈-连杆螺栓位",
      "is_new_l3": true,
      "boundary_note": null,
      "parallel_with": null,
      "duration_estimate": "1-2"
    },
    {
      "step_order": 31,
      "human_description": "将扭矩扳手套筒对准连杆螺栓六角头",
      "l1_id": "L1-07",
      "l1_name": "约束路径操作",
      "l2_id": "L2-07-01",
      "l2_name": "直线插入",
      "l3_id": "L3-07-01-003",
      "l3_name": "插入-套筒套入螺栓头-间隙配合",
      "is_new_l3": true,
      "boundary_note": null,
      "parallel_with": null,
      "duration_estimate": "2-4"
    },
    {
      "step_order": 32,
      "human_description": "使用扭矩扳手旋拧连杆螺栓至定扭矩",
      "l1_id": "L1-06",
      "l1_name": "旋转操作",
      "l2_id": "L2-06-01",
      "l2_name": "工具辅助旋拧",
      "l3_id": "L3-06-01-001",
      "l3_name": "工具旋拧-扭矩扳手-定扭矩紧固",
      "is_new_l3": true,
      "boundary_note": null,
      "parallel_with": null,
      "duration_estimate": "5-15"
    },
    {
      "step_order": 33,
      "human_description": "听觉感知扭矩扳手达到设定值的响声",
      "l1_id": "L1-09",
      "l1_name": "感知定位运动",
      "l2_id": "L2-09-05",
      "l2_name": "听觉定位侧听",
      "l3_id": "L3-09-05-001",
      "l3_name": "侧听-扭矩扳手响声-扭矩到位确认",
      "is_new_l3": true,
      "boundary_note": null,
      "parallel_with": "32",
      "duration_estimate": "0.5-1"
    },
    {
      "step_order": 34,
      "human_description": "抽出扭矩扳手套筒离开螺栓头",
      "l1_id": "L1-07",
      "l1_name": "约束路径操作",
      "l2_id": "L2-07-02",
      "l2_name": "直线抽出",
      "l3_id": "L3-07-02-002",
      "l3_name": "抽出-套筒脱螺栓头-无阻力",
      "is_new_l3": true,
      "boundary_note": null,
      "parallel_with": null,
      "duration_estimate": "1-2"
    },
    {
      "step_order": 35,
      "human_description": "行走移至下一个螺栓位置（重复螺栓紧固流程）",
      "l1_id": "L1-01",
      "l1_name": "全身位移",
      "l2_id": "L2-01-01",
      "l2_name": "平地直行",
      "l3_id": "L3-01-01-001",
      "l3_name": "行走-车间环氧地坪-匀速",
      "is_new_l3": false,
      "boundary_note": null,
      "parallel_with": null,
      "duration_estimate": "2-5"
    },
    {
      "step_order": 36,
      "human_description": "起身恢复站立",
      "l1_id": "L1-02",
      "l1_name": "躯体姿态调整",
      "l2_id": "L2-02-02",
      "l2_name": "弯腰俯身",
      "l3_id": "L3-02-02-002",
      "l3_name": "俯身-起身复位-站立姿态",
      "is_new_l3": false,
      "boundary_note": null,
      "parallel_with": null,
      "duration_estimate": "1-2"
    },
    {
      "step_order": 37,
      "human_description": "行走至喷油器存放区",
      "l1_id": "L1-01",
      "l1_name": "全身位移",
      "l2_id": "L2-01-01",
      "l2_name": "平地直行",
      "l3_id": "L3-01-01-001",
      "l3_name": "行走-车间环氧地坪-匀速",
      "is_new_l3": false,
      "boundary_note": null,
      "parallel_with": null,
      "duration_estimate": "3-8"
    },
    {
      "step_order": 38,
      "human_description": "伸手至喷油器存放位",
      "l1_id": "L1-03",
      "l1_name": "上肢空间运动",
      "l2_id": "L2-03-01",
      "l2_name": "空载伸达",
      "l3_id": "L3-03-01-004",
      "l3_name": "伸达-精密零件存放位-无障碍",
      "is_new_l3": true,
      "boundary_note": null,
      "parallel_with": null,
      "duration_estimate": "1-2"
    },
    {
      "step_order": 39,
      "human_description": "精密捏取喷油器本体",
      "l1_id": "L1-04",
      "l1_name": "手部抓握操控",
      "l2_id": "L2-04-02",
      "l2_name": "精密捏取",
      "l3_id": "L3-04-02-001",
      "l3_name": "捏取-三指捏持-精密喷油器",
      "is_new_l3": true,
      "boundary_note": null,
      "parallel_with": null,
      "duration_estimate": "2-4"
    },
    {
      "step_order": 40,
      "human_description": "精确对位将喷油器插入喷油器安装孔",
      "l1_id": "L1-07",
      "l1_name": "约束路径操作",
      "l2_id": "L2-07-03",
      "l2_name": "多轴对位插接",
      "l3_id": "L3-07-03-001",
      "l3_name": "对接-喷油器安装孔-4自由度对准",
      "is_new_l3": true,
      "boundary_note": "喷油器需XY位置+角度对准+轴向插入，属于多轴对位",
      "parallel_with": null,
      "duration_estimate": "10-20"
    },
    {
      "step_order": 41,
      "human_description": "徒手旋拧喷油器压紧螺母初步固定",
      "l1_id": "L1-06",
      "l1_name": "旋转操作",
      "l2_id": "L2-06-02",
      "l2_name": "徒手旋拧",
      "l3_id": "L3-06-02-001",
      "l3_name": "手拧-喷油器压紧螺母-顺时针预紧",
      "is_new_l3": true,
      "boundary_note": null,
      "parallel_with": null,
      "duration_estimate": "3-8"
    },
    {
      "step_order": 42,
      "human_description": "行走将扭矩扳手归位至工具架",
      "l1_id": "L1-01",
      "l1_name": "全身位移",
      "l2_id": "L2-01-01",
      "l2_name": "平地直行",
      "l3_id": "L3-01-01-001",
      "l3_name": "行走-车间环氧地坪-匀速",
      "is_new_l3": false,
      "boundary_note": null,
      "parallel_with": null,
      "duration_estimate": "3-8"
    }
  ],
  "new_l3_definitions": [
    {
      "l3_id": "L3-01-01-001",
      "l3_name_zh": "行走-车间环氧地坪-匀速",
      "l3_name_en": "Walk-EpoxyFloor-SteadyPace",
      "parent_l2_id": "L2-01-01",
      "description": "在工业车间环氧树脂涂层地坪上以稳定速度直线行走",
      "object_category": "地面",
      "parameter_ranges": {
        "size_range": "行走距离1-30m",
        "weight_range": "N/A",
        "force_range": "N/A",
        "precision_requirement": "路径偏差±20cm"
      },
      "is_new": true,
      "source_scene": "SCENE-37-373-3734-001"
    },
    {
      "l3_id": "L3-01-08-001",
      "l3_name_zh": "停位-装配工位标定点-厘米级",
      "l3_name_en": "StopPosition-AssemblyStation-CentimeterLevel",
      "parent_l2_id": "L2-01-08",
      "description": "在装配工位的地面标定点处精确停止站立",
      "object_category": "定位标记",
      "parameter_ranges": {
        "size_range": "标定点直径5-10cm",
        "weight_range": "N/A",
        "force_range": "N/A",
        "precision_requirement": "位置精度±3cm"
      },
      "is_new": true,
      "source_scene": "SCENE-37-373-3734-001"
    },
    {
      "l3_id": "L3-09-07-001",
      "l3_name_zh": "读取-装配作业指导书-工艺参数",
      "l3_name_en": "Read-AssemblyWorkInstruction-ProcessParams",
      "parent_l2_id": "L2-09-07",
      "description": "读取作业指导书上的装配顺序、扭矩要求等工艺参数信息",
      "object_category": "作业文件",
      "parameter_ranges": {
        "size_range": "A4-A3纸张",
        "weight_range": "N/A",
        "force_range": "N/A",
        "precision_requirement": "文字识别精度>99%"
      },
      "is_new": true,
      "source_scene": "SCENE-37-373-3734-001"
    },
    {
      "l3_id": "L3-02-04-001",
      "l3_name_zh": "转体-90度-向物料区",
      "l3_name_en": "TurnBody-90Degree-ToMaterialArea",
      "parent_l2_id": "L2-02-04",
      "description": "原地转动躯干约90度面向物料存放区",
      "object_category": "N/A",
      "parameter_ranges": {
        "size_range": "N/A",
        "weight_range": "N/A",
        "force_range": "N/A",
        "precision_requirement": "旋转角度±10度"
      },
      "is_new": true,
      "source_scene": "SCENE-37-373-3734-001"
    },
    {
      "l3_id": "L3-03-01-001",
      "l3_name_zh": "伸达-起重遥控器悬挂位-无障碍",
      "l3_name_en": "Reach-CraneRemoteHangingPos-Clear",
      "parent_l2_id": "L2-03-01",
      "description": "将手伸向悬挂的起重设备遥控器位置准备拿取",
      "object_category": "控制设备",
      "parameter_ranges": {
        "size_range": "伸达距离30-80cm",
        "weight_range": "N/A",
        "force_range": "N/A",
        "precision_requirement": "末端定位±5cm"
      },
      "is_new": true,
      "source_scene": "SCENE-37-373-3734-001"
    },
    {
      "l3_id": "L3-04-03-001",
      "l3_name_zh": "工具握持-起重遥控器-操控功能姿",
      "l3_name_en": "ToolGrip-CraneRemote-ControlPosture",
      "parent_l2_id": "L2-04-03",
      "description": "以能够操作按钮的功能姿势握持起重设备遥控器",
      "object_category": "控制设备",
      "parameter_ranges": {
        "size_range": "遥控器长度15-25cm",
        "weight_range": "0.3-0.8kg",
        "force_range": "握力5-15N",
        "precision_requirement": "拇指可触及所有按钮"
      },
      "is_new": true,
      "source_scene": "SCENE-37-373-3734-001"
    },
    {
      "l3_id": "L3-05-01-001",
      "l3_name_zh": "点压-起重遥控按钮-轻力度",
      "l3_name_en": "Press-CraneRemoteButton-LightForce",
      "parent_l2_id": "L2-05-01",
      "description": "用手指点压起重遥控器的方向/升降按钮",
      "object_category": "控制按钮",
      "parameter_ranges": {
        "size_range": "按钮直径10-20mm",
        "weight_range": "N/A",
        "force_range": "2-8N",
        "precision_requirement": "按压准确率100%"
      },
      "is_new": true,
      "source_scene": "SCENE-37-373-3734-001"
    },
    {
      "l3_id": "L3-09-01-001",
      "l3_name_zh": "注视-起重设备吊钩-位置确认",
      "l3_name_en": "Gaze-CraneHook-PositionConfirm",
      "parent_l2_id": "L2-09-01",
      "description": "视线对准起重设备吊钩确认其空间位置",
      "object_category": "起重设备",
      "parameter_ranges": {
        "size_range": "吊钩尺寸10-30cm",
        "weight_range": "N/A",
        "force_range": "N/A",
        "precision_requirement": "位置判断精度±10cm"
      },
      "is_new": true,
      "source_scene": "SCENE-37-373-3734-001"
    },
    {
      "l3_id": "L3-04-07-001",
      "l3_name_zh": "释放-渐进松指-遥控器悬挂",
      "l3_name_en": "Release-GradualLoosen-RemoteHang",
      "parent_l2_id": "L2-04-07",
      "description": "逐渐松开手指释放遥控器使其回到悬挂位置",
      "object_category": "控制设备",
      "parameter_ranges": {
        "size_range": "N/A",
        "weight_range": "0.3-0.8kg",
        "force_range": "N/A",
        "precision_requirement": "释放速度可控"
      },
      "is_new": true,
      "source_scene": "SCENE-37-373-3734-001"
    },
    {
      "l3_id": "L3-02-02-001",
      "l3_name_zh": "俯身-中度前屈-工件吊耳高度",
      "l3_name_en": "BendDown-ModerateFlex-LiftingLugHeight",
      "parent_l2_id": "L2-02-02",
      "description": "前屈弯腰使双手能够触及工件吊耳高度位置",
      "object_category": "N/A",
      "parameter_ranges": {
        "size_range": "目标高度50-100cm",
        "weight_range": "N/A",
        "force_range": "N/A",
        "precision_requirement": "手部到达高度±5cm"
      },
      "is_new": true,
      "source_scene": "SCENE-37-373-3734-001"
    },
    {
      "l3_id": "L3-03-01-002",
      "l3_name_zh": "伸达-吊具钩环-短距直线",
      "l3_name_en": "Reach-LiftingHookRing-ShortLinear",
      "parent_l2_id": "L2-03-01",
      "description": "短距离直线伸手至吊具钩环位置",
      "object_category": "吊具",
      "parameter_ranges": {
        "size_range": "伸达距离20-50cm",
        "weight_range": "N/A",
        "force_range": "N/A",
        "precision_requirement": "末端定位±3cm"
      },
      "is_new": true,
      "source_scene": "SCENE-37-373-3734-001"
    },
    {
      "l3_id": "L3-04-01-001",
      "l3_name_zh": "力握-圆环-直径15至30mm",
      "l3_name_en": "PowerGrip-Ring-Diameter15to30mm",
      "parent_l2_id": "L2-04-01",
      "description": "全手包络抓握圆环形状的吊具钩环",
      "object_category": "吊具",
      "parameter_ranges": {
        "size_range": "环直径15-30mm",
        "weight_range": "0.5-2kg",
        "force_range": "握力20-50N",
        "precision_requirement": "抓握稳定"
      },
      "is_new": true,
      "source_scene": "SCENE-37-373-3734-001"
    },
    {
      "l3_id": "L3-07-01-001",
      "l3_name_zh": "插入-吊钩入吊耳孔-间隙5mm",
      "l3_name_en": "Insert-HookIntoLiftingLugHole-5mmClearance",
      "parent_l2_id": "L2-07-01",
      "description": "将吊钩插入工件吊耳孔中完成挂接",
      "object_category": "吊具连接",
      "parameter_ranges": {
        "size_range": "孔径20-50mm",
        "weight_range": "N/A",
        "force_range": "插入力<10N",
        "precision_requirement": "对准精度±5mm"
      },
      "is_new": true,
      "source_scene": "SCENE-37-373-3734-001"
    },
    {
      "l3_id": "L3-02-02-002",
      "l3_name_zh": "俯身-起身复位-站立姿态",
      "l3_name_en": "BendDown-StandUpRecover-StandingPosture",
      "parent_l2_id": "L2-02-02",
      "description": "从弯腰姿态恢复至直立站立姿态",
      "object_category": "N/A",
      "parameter_ranges": {
        "size_range": "N/A",
        "weight_range": "N/A",
        "force_range": "N/A",
        "precision_requirement": "恢复完全直立"
      },
      "is_new": true,
      "source_scene": "SCENE-37-373-3734-001"
    },
    {
      "l3_id": "L3-01-07-001",
      "l3_name_zh": "负载行走-起重引导-遥控持握",
      "l3_name_en": "LoadedWalk-CraneGuiding-RemoteHolding",
      "parent_l2_id": "L2-01-07",
      "description": "手持起重遥控器边走边引导悬吊的重型工件移动",
      "object_category": "重型工件",
      "parameter_ranges": {
        "size_range": "引导距离5-20m",
        "weight_range": "工件重100-500kg",
        "force_range": "遥控器操作力<10N",
        "precision_requirement": "跟随工件移动路径"
      },
      "is_new": true,
      "source_scene": "SCENE-37-373-3734-001"
    },
    {
      "l3_id": "L3-05-06-001",
      "l3_name_zh": "抵持-悬吊重件-水平稳定",
      "l3_name_en": "Brace-SuspendedHeavyPart-HorizontalStable",
      "parent_l2_id": "L2-05-06",
      "description": "单手或双手抵住悬吊的重型部件防止水平晃动",
      "object_category": "重型工件",
      "parameter_ranges": {
        "size_range": "工件直径200-800mm",
        "weight_range": "50-500kg",
        "force_range": "抵持力10-50N",
        "precision_requirement": "晃动控制±5cm"
      },
      "is_new": true,
      "source_scene": "SCENE-37-373-3734-001"
    },
    {
      "l3_id": "L3-09-01-002",
      "l3_name_zh": "注视-装配配合面-对准确认",
      "l3_name_en": "Gaze-AssemblyMatingFace-AlignmentConfirm",
      "parent_l2_id": "L2-09-01",
      "description": "视线对准两个待装配零件的配合面确认对准状态",
      "object_category": "装配配合面",
      "parameter_ranges": {
        "size_range": "配合面直径100-600mm",
        "weight_range": "N/A",
        "force_range": "N/A",
        "precision_requirement": "对准偏差判断±2mm"
      },
      "is_new": true,
      "source_scene": "SCENE-37-373-3734-001"
    },
    {
      "l3_id": "L3-05-01-002",
      "l3_name_zh": "点压-起重遥控微动按钮-精确定位",
      "l3_name_en": "Press-CraneRemoteInchButton-PrecisePosition",
      "parent_l2_id": "L2-05-01",
      "description": "点压起重遥控器微动按钮进行精确位置微调",
      "object_category": "控制按钮",
      "parameter_ranges": {
        "size_range": "按钮直径10-15mm",
        "weight_range": "N/A",
        "force_range": "2-5N",
        "precision_requirement": "单次移动量<10mm"
      },
      "is_new": true,
      "source_scene": "SCENE-37-373-3734-001"
    },
    {
      "l3_id": "L3-07-01-002",
      "l3_name_zh": "插入-缸套入缸体孔-精密间隙配合",
      "l3_name_en": "Insert-CylinderLinerIntoBlock-PrecisionFit",
      "parent_l2_id": "L2-07-01",
      "description": "引导缸套沿轴向精密插入缸体安装孔完成配合",
      "object_category": "缸套",
      "parameter_ranges": {
        "size_range": "缸套直径150-400mm",
        "weight_range": "50-200kg",
        "force_range": "插入力50-500N",
        "precision_requirement": "配合间隙0.02-0.1mm"
      },
      "is_new": true,
      "source_scene": "SCENE-37-373-3734-001"
    },
    {
      "l3_id": "L3-09-02-001",
      "l3_name_zh": "贴检-配合面间隙-装配到位确认",
      "l3_name_en": "CloseInspect-MatingGap-AssemblyConfirm",
      "parent_l2_id": "L2-09-02",
      "description": "近距离检视两零件配合面间隙确认装配到位",
      "object_category": "配合面",
      "parameter_ranges": {
        "size_range": "观察距离<200mm",
        "weight_range": "N/A",
        "force_range": "N/A",
        "precision_requirement": "间隙判断精度±0.1mm"
      },
      "is_new": true,
      "source_scene": "SCENE-37-373-3734-001"
    },
    {
      "l3_id": "L3-07-02-001",
      "l3_name_zh": "抽出-吊钩脱吊耳-无阻力",
      "l3_name_en": "Withdraw-HookFromLiftingLug-NoResist",
      "parent_l2_id": "L2-07-02",
      "description": "将吊钩从工件吊耳孔中抽出脱开连接",
      "object_category": "吊具连接",
      "parameter_ranges": {
        "size_range": "孔径20-50mm",
        "weight_range": "N/A",
        "force_range": "抽出力<10N",
        "precision_requirement": "轴向抽出"
      },
      "is_new": true,
      "source_scene": "SCENE-37-373-3734-001"
    },
    {
      "l3_id": "L3-03-01-003",
      "l3_name_zh": "伸达-工具架工具位-短距直线",
      "l3_name_en": "Reach-ToolRackPosition-ShortLinear",
      "parent_l2_id": "L2-03-01",
      "description": "伸手至工具架上工具存放位置准备拿取",
      "object_category": "工具架",
      "parameter_ranges": {
        "size_range": "伸达距离30-60cm",
        "weight_range": "N/A",
        "force_range": "N/A",
        "precision_requirement": "末端定位±3cm"
      },
      "is_new": true,
      "source_scene": "SCENE-37-373-3734-001"
    },
    {
      "l3_id": "L3-04-03-002",
      "l3_name_zh": "工具握持-扭矩扳手-旋拧功能姿",
      "l3_name_en": "ToolGrip-TorqueWrench-TorquePosture",
      "parent_l2_id": "L2-04-03",
      "description": "以能够施加旋转力矩的功能姿势握持扭矩扳手手柄",
      "object_category": "扭矩扳手",
      "parameter_ranges": {
        "size_range": "手柄长度200-500mm",
        "weight_range": "1-5kg",
        "force_range": "握力30-80N",
        "precision_requirement": "握持稳定无滑动"
      },
      "is_new": true,
      "source_scene": "SCENE-37-373-3734-001"
    },
    {
      "l3_id": "L3-03-02-001",
      "l3_name_zh": "转移-手持工具-近距",
      "l3_name_en": "Transfer-HandheldTool-ShortDist",
      "parent_l2_id": "L2-03-02",
      "description": "单手持握工具从工具架转移至操作位置",
      "object_category": "手工具",
      "parameter_ranges": {
        "size_range": "转移距离0.5-3m",
        "weight_range": "0.5-5kg",
        "force_range": "N/A",
        "precision_requirement": "工具姿态保持"
      },
      "is_new": true,
      "source_scene": "SCENE-37-373-3734-001"
    },
    {
      "l3_id": "L3-02-02-003",
      "l3_name_zh": "俯身-深度前屈-连杆螺栓位",
      "l3_name_en": "BendDown-DeepFlex-ConrodBoltPos",
      "parent_l2_id": "L2-02-02",
      "description": "深度前屈弯腰使工具能够到达连杆螺栓位置",
      "object_category": "N/A",
      "parameter_ranges": {
        "size_range": "目标高度30-70cm",
        "weight_range": "N/A",
        "force_range": "N/A",
        "precision_requirement": "工具到位±3cm"
      },
      "is_new": true,
      "source_scene": "SCENE-37-373-3734-001"
    },
    {
      "l3_id": "L3-07-01-003",
      "l3_name_zh": "插入-套筒套入螺栓头-间隙配合",
      "l3_name_en": "Insert-SocketOnBoltHead-ClearanceFit",
      "parent_l2_id": "L2-07-01",
      "description": "将扭矩扳手套筒对准并套入螺栓六角头",
      "object_category": "螺栓",
      "parameter_ranges": {
        "size_range": "螺栓规格M16-M36",
        "weight_range": "N/A",
        "force_range": "插入力<20N",
        "precision_requirement": "对中精度±1mm"
      },
      "is_new": true,
      "source_scene": "SCENE-37-373-3734-001"
    },
    {
      "l3_id": "L3-06-01-001",
      "l3_name_zh": "工具旋拧-扭矩扳手-定扭矩紧固",
      "l3_name_en": "ToolTorque-TorqueWrench-TargetTorqueFasten",
      "parent_l2_id": "L2-06-01",
      "description": "使用扭矩扳手旋拧螺栓至预设扭矩值",
      "object_category": "螺栓",
      "parameter_ranges": {
        "size_range": "螺栓规格M16-M36",
        "weight_range": "N/A",
        "force_range": "扭矩100-500Nm",
        "precision_requirement": "扭矩精度±3%"
      },
      "is_new": true,
      "source_scene": "SCENE-37-373-3734-001"
    },
    {
      "l3_id": "L3-09-05-001",
      "l3_name_zh": "侧听-扭矩扳手响声-扭矩到位确认",
      "l3_name_en": "Listen-TorqueWrenchClick-TorqueConfirm",
      "parent_l2_id": "L2-09-05",
      "description": "通过听觉感知扭矩扳手达到设定值时的卡嗒声确认到位",
      "object_category": "扭矩扳手",
      "parameter_ranges": {
        "size_range": "N/A",
        "weight_range": "N/A",
        "force_range": "N/A",
        "precision_requirement": "声音识别准确"
      },
      "is_new": true,
      "source_scene": "SCENE-37-373-3734-001"
    },
    {
      "l3_id": "L3-07-02-002",
      "l3_name_zh": "抽出-套筒脱螺栓头-无阻力",
      "l3_name_en": "Withdraw-SocketFromBoltHead-NoResist",
      "parent_l2_id": "L2-07-02",
      "description": "将扭矩扳手套筒从螺栓头抽离",
      "object_category": "螺栓",
      "parameter_ranges": {
        "size_range": "螺栓规格M16-M36",
        "weight_range": "N/A",
        "force_range": "抽出力<10N",
        "precision_requirement": "轴向抽出"
      },
      "is_new": true,
      "source_scene": "SCENE-37-373-3734-001"
    },
    {
      "l3_id": "L3-03-01-004",
      "l3_name_zh": "伸达-精密零件存放位-无障碍",
      "l3_name_en": "Reach-PrecisionPartStoragePos-Clear",
      "parent_l2_id": "L2-03-01",
      "description": "伸手至精密零件存放位置准备取件",
      "object_category": "精密零件",
      "parameter_ranges": {
        "size_range": "伸达距离30-60cm",
        "weight_range": "N/A",
        "force_range": "N/A",
        "precision_requirement": "末端定位±2cm"
      },
      "is_new": true,
      "source_scene": "SCENE-37-373-3734-001"
    },
    {
      "l3_id": "L3-04-02-001",
      "l3_name_zh": "捏取-三指捏持-精密喷油器",
      "l3_name_en": "Pinch-ThreeFingerGrip-PrecisionInjector",
      "parent_l2_id": "L2-04-02",
      "description": "用拇指、食指、中指三指精密捏取喷油器本体",
      "object_category": "喷油器",
      "parameter_ranges": {
        "size_range": "直径20-40mm，长度80-150mm",
        "weight_range": "0.5-2kg",
        "force_range": "捏持力5-15N",
        "precision_requirement": "不触碰精密配合面"
      },
      "is_new": true,
      "source_scene": "SCENE-37-373-3734-001"
    },
    {
      "l3_id": "L3-07-03-001",
      "l3_name_zh": "对接-喷油器安装孔-4自由度对准",
      "l3_name_en": "Dock-InjectorMountingHole-4DOFAlign",
      "parent_l2_id": "L2-07-03",
      "description": "将喷油器XY位置、角度对准后插入安装孔",
      "object_category": "喷油器",
      "parameter_ranges": {
        "size_range": "安装孔直径25-45mm",
        "weight_range": "0.5-2kg",
        "force_range": "插入力10-50N",
        "precision_requirement": "位置精度±0.5mm，角度±1度"
      },
      "is_new": true,
      "source_scene": "SCENE-37-373-3734-001"
    },
    {
      "l3_id": "L3-06-02-001",
      "l3_name_zh": "手拧-喷油器压紧螺母-顺时针预紧",
      "l3_name_en": "HandTighten-InjectorClampNut-CWPretighten",
      "parent_l2_id": "L2-06-02",
      "description": "徒手顺时针旋拧喷油器压紧螺母进行预紧固定",
      "object_category": "压紧螺母",
      "parameter_ranges": {
        "size_range": "螺母规格M14-M24",
        "weight_range": "N/A",
        "force_range": "手拧扭矩5-15Nm",
        "precision_requirement": "预紧到位手感判断"
      },
      "is_new": true,
      "source_scene": "SCENE-37-373-3734-001"
    }
  ],
  "l2_usage_summary": {
    "涉及的L2编号列表": [
      "L2-01-01",
      "L2-01-07",
      "L2-01-08",
      "L2-02-02",
      "L2-02-04",
      "L2-03-01",
      "L2-03-02",
      "L2-04-01",
      "L2-04-02",
      "L2-04-03",
      "L2-04-07",
      "L2-05-01",
      "L2-05-06",
      "L2-06-01",
      "L2-06-02",
      "L2-07-01",
      "L2-07-02",
      "L2-07-03",
      "L2-09-01",
      "L2-09-02",
      "L2-09-05",
      "L2-09-07"
    ],
    "最高频L2": "L2-01-01",
    "涉及的L1数量": 9
  }
}